django_dev/__init__.py
django_dev/dev.py
django_dev-0.2.1.data/scripts/django-dev
django_dev-0.2.1.dist-info/DESCRIPTION.rst
django_dev-0.2.1.dist-info/METADATA
django_dev-0.2.1.dist-info/RECORD
django_dev-0.2.1.dist-info/WHEEL
django_dev-0.2.1.dist-info/metadata.json
django_dev-0.2.1.dist-info/top_level.txt
